[
  {
    "id": "adulte_001_pourquoi_les_rendez_vous_modernes_ressemblent_ils_",
    "setup": "Pourquoi les rendez-vous modernes ressemblent-ils au Wi-Fi ?",
    "punchline": "Beaucoup de connexion au début, puis quelqu'un disparaît sans prévenir.",
    "category": "adulte",
    "adult": true
  },
  {
    "id": "adulte_002_mon_ex_m_a_dit_qu_il_elle_avait_change",
    "setup": "Mon ex m'a dit qu'il/elle avait changé.",
    "punchline": "Oui, de partenaire surtout.",
    "category": "adulte",
    "adult": true
  },
  {
    "id": "adulte_003_pourquoi_les_draps_sont_ils_les_meilleurs_temoins",
    "setup": "Pourquoi les draps sont-ils les meilleurs témoins ?",
    "punchline": "Parce qu'ils savent tout et restent toujours couchés.",
    "category": "adulte",
    "adult": true
  },
  {
    "id": "adulte_004_j_ai_voulu_etre_raisonnable_pendant_une_soiree",
    "setup": "J'ai voulu être raisonnable pendant une soirée.",
    "punchline": "Le concept n'a pas passé l'entrée.",
    "category": "adulte",
    "adult": true
  },
  {
    "id": "adulte_005_le_flirt_c_est_simple",
    "setup": "Le flirt, c'est simple.",
    "punchline": "Tu relis un message douze fois pour répondre « haha oui ».",
    "category": "adulte",
    "adult": true
  },
  {
    "id": "adulte_006_pourquoi_les_crushs_aiment_ils_repondre_apres_troi",
    "setup": "Pourquoi les crushs aiment-ils répondre après trois heures ?",
    "punchline": "Pour laisser le temps à ton cerveau d'écrire une trilogie.",
    "category": "adulte",
    "adult": true
  },
  {
    "id": "adulte_007_mon_telephone_connait_trop_bien_ma_vie_sentimental",
    "setup": "Mon téléphone connaît trop bien ma vie sentimentale.",
    "punchline": "Il propose automatiquement le mode silencieux.",
    "category": "adulte",
    "adult": true
  },
  {
    "id": "adulte_008_j_ai_demande_a_mon_ex_de_rester_dans_le_passe",
    "setup": "J'ai demandé à mon ex de rester dans le passé.",
    "punchline": "Il/elle a répondu à ma story.",
    "category": "adulte",
    "adult": true
  },
  {
    "id": "adulte_009_pourquoi_les_applications_de_rencontre_ressemblent",
    "setup": "Pourquoi les applications de rencontre ressemblent-elles à un frigo ?",
    "punchline": "On ouvre souvent, mais rien ne nous tente vraiment.",
    "category": "adulte",
    "adult": true
  },
  {
    "id": "adulte_010_le_probleme_avec_les_messages_tu_dors",
    "setup": "Le problème avec les messages « tu dors ? » ?",
    "punchline": "Ils arrivent toujours quand la dignité, elle, dort déjà.",
    "category": "adulte",
    "adult": true
  },
  {
    "id": "adulte_011_j_ai_essaye_de_garder_mes_standards_tres_hauts",
    "setup": "J'ai essayé de garder mes standards très hauts.",
    "punchline": "Puis quelqu'un de drôle m'a regardé.",
    "category": "adulte",
    "adult": true
  },
  {
    "id": "adulte_012_pourquoi_les_relations_compliquees_durent_elles_si",
    "setup": "Pourquoi les relations compliquées durent-elles si longtemps ?",
    "punchline": "Parce que personne ne trouve le bouton « quitter la partie ».",
    "category": "adulte",
    "adult": true
  },
  {
    "id": "adulte_013_mon_type_ideal",
    "setup": "Mon type idéal ?",
    "punchline": "Quelqu'un qui ne transforme pas « vu à 22:14 » en thriller psychologique.",
    "category": "adulte",
    "adult": true
  },
  {
    "id": "adulte_014_j_ai_supprime_le_numero_de_mon_ex",
    "setup": "J'ai supprimé le numéro de mon ex.",
    "punchline": "Heureusement, ma mémoire a refusé de coopérer.",
    "category": "adulte",
    "adult": true
  },
  {
    "id": "adulte_015_pourquoi_le_flirt_apres_minuit_est_il_dangereux",
    "setup": "Pourquoi le flirt après minuit est-il dangereux ?",
    "punchline": "Parce que le bon sens a déjà fini son service.",
    "category": "adulte",
    "adult": true
  },
  {
    "id": "adulte_016_j_ai_dit_que_je_ne_retomberais_jamais_dans_le_pann",
    "setup": "J'ai dit que je ne retomberais jamais dans le panneau.",
    "punchline": "Le panneau était très beau.",
    "category": "adulte",
    "adult": true
  },
  {
    "id": "adulte_017_la_maturite_sentimentale_c_est_quoi",
    "setup": "La maturité sentimentale, c'est quoi ?",
    "punchline": "Écrire le message, le relire, puis ne pas l'envoyer.",
    "category": "adulte",
    "adult": true
  },
  {
    "id": "adulte_018_pourquoi_les_red_flags_sont_ils_parfois_invisibles",
    "setup": "Pourquoi les red flags sont-ils parfois invisibles ?",
    "punchline": "Parce qu'on les regarde avec des lunettes roses.",
    "category": "adulte",
    "adult": true
  },
  {
    "id": "adulte_019_mon_cur_dit_oui_mon_cerveau_dit_non",
    "setup": "Mon cœur dit oui, mon cerveau dit non.",
    "punchline": "Mon groupe d'amis a déjà préparé le PowerPoint.",
    "category": "adulte",
    "adult": true
  },
  {
    "id": "adulte_020_pourquoi_certaines_histoires_commencent_elles_par_",
    "setup": "Pourquoi certaines histoires commencent-elles par « c'était juste pour une nuit » ?",
    "punchline": "Parce que la vie adore les saisons supplémentaires.",
    "category": "adulte",
    "adult": true
  },
  {
    "id": "adulte_021_j_ai_demande_de_l_espace_dans_ma_relation",
    "setup": "J'ai demandé de l'espace dans ma relation.",
    "punchline": "On m'a offert un abonnement cloud.",
    "category": "adulte",
    "adult": true
  },
  {
    "id": "adulte_022_le_vrai_signe_d_intimite",
    "setup": "Le vrai signe d'intimité ?",
    "punchline": "Pouvoir demander « tu peux me passer mon chargeur ? » sans préciser lequel.",
    "category": "adulte",
    "adult": true
  },
  {
    "id": "adulte_023_pourquoi_une_conversation_osee_devient_elle_genant",
    "setup": "Pourquoi une conversation osée devient-elle gênante au réveil ?",
    "punchline": "Le soleil active les mises à jour de la honte.",
    "category": "adulte",
    "adult": true
  },
  {
    "id": "adulte_024_j_ai_jure_de_ne_plus_ecrire_a_mon_ex",
    "setup": "J'ai juré de ne plus écrire à mon ex.",
    "punchline": "J'ai techniquement envoyé un vocal.",
    "category": "adulte",
    "adult": true
  },
  {
    "id": "adulte_025_pourquoi_les_coups_de_foudre_sont_ils_mal_organise",
    "setup": "Pourquoi les coups de foudre sont-ils mal organisés ?",
    "punchline": "Ils arrivent toujours quand tu avais décidé de rester tranquille.",
    "category": "adulte",
    "adult": true
  },
  {
    "id": "adulte_026_mon_flirt_prefere",
    "setup": "Mon flirt préféré ?",
    "punchline": "Celui où les deux savent très bien ce qu'il se passe mais font semblant d'être surpris.",
    "category": "adulte",
    "adult": true
  },
  {
    "id": "adulte_027_pourquoi_le_fameux_on_verra_est_il_si_puissant",
    "setup": "Pourquoi le fameux « on verra » est-il si puissant ?",
    "punchline": "Parce qu'il peut contenir un date, un ghosting et une catastrophe.",
    "category": "adulte",
    "adult": true
  },
  {
    "id": "adulte_028_j_ai_voulu_jouer_la_personne_inaccessible",
    "setup": "J'ai voulu jouer la personne inaccessible.",
    "punchline": "J'ai répondu en huit secondes.",
    "category": "adulte",
    "adult": true
  },
  {
    "id": "adulte_029_pourquoi_certaines_attirances_sont_elles_de_mauvai",
    "setup": "Pourquoi certaines attirances sont-elles de mauvaises idées ?",
    "punchline": "Parce que les meilleures anecdotes ont rarement commencé par une décision raisonnable.",
    "category": "adulte",
    "adult": true
  },
  {
    "id": "adulte_030_j_ai_demande_un_signe_a_l_univers_sur_mon_crush",
    "setup": "J'ai demandé un signe à l'univers sur mon crush.",
    "punchline": "Il/elle a liké une photo de 2022. Beaucoup trop de signes, finalement.",
    "category": "adulte",
    "adult": true
  }
]